LICENSE
README.md
setup.py
bdgd2dss/__init__.py
bdgd2dss/bdgd2dss.py
bdgd2dss/dicionarios.py
bdgd2dss.egg-info/PKG-INFO
bdgd2dss.egg-info/SOURCES.txt
bdgd2dss.egg-info/dependency_links.txt
bdgd2dss.egg-info/requires.txt
bdgd2dss.egg-info/top_level.txt