Metadata-Version: 2.1
Name: bdgd2dss
Version: 0.0.5
Summary: Ferramenta para modelagem de alimentadores da BDGD para uso com OpenDSS
Author: Arthur Gomes de Souza
Author-email: arthurgomesba@gmail.com
Maintainer: Wellington Maycon Santos Bernardes
Maintainer-email: wmsbernardes@ufu.br
License: MIT License
Keywords: bdgd2dss bdgd
Classifier: Programming Language :: Python :: 3
Classifier: License :: OSI Approved :: MIT License
Classifier: Operating System :: OS Independent
Requires-Python: >=3.7
License-File: LICENSE
